{
"description": "Word jumble sets where the pangram (word that uses all given letters) is 5 letters long.",
"wordSets": [
{"pangram": ["abend", "bandanaed", "baned", "beaned"], "validLetters": ["a", "b", "d", "e", "n"], "answers": ["aband", "abede", "addda", "added", "addenda", "adead", "anan", "anba", "anded", "anend", "bandanna", "beaded", "bedead", "bedeen", "bedene", "beebee", "been", "benab", "benben", "bendee", "dabb", "dabbed", "danda", "dead", "deaden", "deaned", "dedd", "dedenda", "deeded", "deedeed", "denda", "enaena", "nabe", "nanda", "nane", "needn", "nene"]},
{"pangram": ["ablaze"], "validLetters": ["a", "b", "e", "l", "z"], "answers": ["abaze", "able", "alae", "alee", "bable", "balza", "beala", "beeball", "beebee", "belee", "bezazz", "bezel", "blae", "bleb", "blee", "bleeze", "ezba", "labbella", "labella"]},
{"pangram": ["argue", "arguer", "augerer", "gauger"], "validLetters": ["a", "e", "g", "r", "u"], "answers": ["aeger", "aggur", "agre", "agree", "ague", "agura", "arage", "arar", "arear", "arrage", "arrear", "aurae", "eager", "eggar", "egre", "euge", "gagee", "garage", "garau", "garg", "garua", "gauge", "gear", "gegg", "gegger", "geraera", "gree", "greegree", "grege", "gregge", "guerre", "gugu", "gurge", "gurr", "guru", "raga", "ragee", "rara", "reagree", "regear", "reggae", "regr", "regurge", "reurge", "ruer", "ruga", "ruru"]},
{"pangram": ["eyelid"], "validLetters": ["d", "e", "i", "l", "y"], "answers": ["dedd", "deeded", "deedeed", "deedy", "deil", "deled", "dely", "diddle", "didy", "didle", "dyed", "diel", "eely", "eide", "eyey", "elided", "idee", "idyll", "idle", "yeel", "yeld", "yelled", "lidded", "lied", "lilied"]},
{"pangram": ["baleen", "balnea", "balneal", "beanball", "enable", "nable"], "validLetters": ["a", "b", "e", "l", "n"], "answers": ["alae", "alee", "anal", "anan", "anba", "anneal", "bable", "beala", "beeball", "beebee", "been", "belee", "benab", "benben", "bennel", "blae", "bleb", "blee", "elne", "enaena", "enleen", "labbella", "labella", "leben", "nabe", "nabla", "nael", "nane", "nebel", "neele", "nene"]},
{"pangram": ["ceint", "centi", "cetin", "enceint", "entice", "intice"], "validLetters": ["c", "e", "i", "n", "t"], "answers": ["cene", "cetene", "cetic", "cincinni", "cine", "cnicin", "ctene", "eeten", "ence", "entete", "eten", "etic", "ictic", "init", "innet", "inti", "intinct", "nene", "nete", "nici", "niece", "nineteen", "teet", "tenent", "tenet", "tent", "tete", "tineine", "tittie"]},
{"pangram": ["arend", "dandered", "darneder", "darner", "deadener", "denar", "endear", "endeared", "ennedra", "errand", "nadder", "narendra", "rander", "reddenda"], "validLetters": ["a", "d", "e", "n", "r"], "answers": ["addda", "added", "addenda", "adder", "addr", "adead", "anan", "anded", "anear", "anend", "annerre", "arar", "arear", "ared", "arenae", "arrear", "dadder", "danda", "dead", "deaden", "deaned", "deare", "dedd", "dedenda", "deeded", "deedeed", "deener", "denda", "derere", "dern", "derned", "dreader", "drear", "dree", "earner", "edder", "enaena", "erred", "nanda", "nane", "nare", "nearer", "needer", "needn", "nene", "nerd", "raanan", "radded", "randan", "randn", "rane", "rara", "readd", "redared", "redder", "reded", "redeed", "reeded", "rended", "render", "rendered", "renn", "renne", "reran", "rereader"]},
{"pangram": ["dippier", "dipppier", "dripped", "drippier", "epeirid", "piperide", "piperidide", "pried", "redipped", "ripped"], "validLetters": ["d", "e", "i", "p", "r"], "answers": ["dedd", "deeded", "deedeed", "deeper", "deirid", "depr", "derere", "derided", "derri", "derride", "derriere", "diddered", "dier", "dipped", "dird", "direr", "dree", "dridder", "dried", "edder", "eerie", "eide", "erred", "idee", "irred", "irride", "pede", "peed", "peep", "peeper", "peerie", "pere", "pipe", "pipi", "pipid", "pipier", "pipped", "pipper", "piripiri", "pirr", "pirrie", "pred", "pree", "preed", "prep", "preppier", "prie", "redder", "reded", "redeed", "reeded", "repipe", "repp", "repr", "ridder", "ripier", "ripper"]},
{"pangram": ["agrafe", "agraffe", "fagger", "farrage", "gerefa", "graffer"], "validLetters": ["a", "e", "f", "g", "r"], "answers": ["aeger", "afara", "afer", "affa", "affeer", "affere", "agre", "agree", "arage", "arar", "arear", "arrage", "arrear", "eager", "eggar", "egre", "faff", "fare", "farer", "fearer", "feere", "fere", "ferr", "free", "gaff", "gagee", "garage", "garg", "garrafa", "gear", "gegg", "gegger", "geraera", "gree", "greegree", "grege", "gregge", "raffee", "raga", "ragee", "rara", "reagree", "refer", "referee", "referrer", "refr", "regear", "reggae", "regr"]},
{"pangram": ["aglare", "alleger", "argel", "argle", "galere", "gallera", "gargle", "gargler", "gregal", "regale", "regaler"], "validLetters": ["a", "e", "g", "l", "r"], "answers": ["aeger", "agal", "agla", "agral", "agre", "agree", "alae", "alee", "algae", "arage", "arar", "areal", "arear", "argala", "arrage", "arrear", "eager", "egall", "eggar", "eggler", "egre", "gagee", "galagala", "galeae", "garage", "garg", "gear", "gegg", "gegger", "gell", "geraera", "glar", "gleg", "graal", "gree", "greegree", "grege", "gregge", "lare", "leer", "raga", "ragee", "rale", "rall", "rara", "reaal", "reagree", "regear", "regel", "reggae", "regr", "rereel"]},
{"pangram": ["revent", "reverent"], "validLetters": ["e", "n", "r", "t", "v"], "answers": ["eeten", "enerve", "entete", "eten", "eterne", "event", "ever", "nene", "nerve", "nerver", "nete", "never", "renerve", "renn", "renne", "rent", "renter", "retree", "reveneer", "rever", "reveree", "revete", "teet", "teevee", "tenent", "tenet", "tent", "tenter", "terete", "terne", "terreen", "tervee", "tete", "tetter", "tret", "trevet", "trevette", "veer", "veneer", "veneerer", "venerer", "venner", "verre", "verve", "verver", "vervet"]},
{"pangram": ["piert", "pitier", "preterit", "pretire", "prettier", "retrip", "rippet", "tipper", "tipree", "tripe"], "validLetters": ["e", "i", "p", "r", "t"], "answers": ["eerie", "epit", "etrier", "irrite", "peep", "peeper", "peerie", "pere", "perter", "piete", "pipe", "pipette", "pipi", "pipier", "pipper", "piripiri", "pirr", "pirrie", "pree", "prep", "preppier", "preter", "prie", "repipe", "repp", "repr", "retie", "retier", "retire", "retiree", "retree", "retrier", "ripier", "ripper", "rite", "teet", "tepe", "tepee", "terete", "terp", "tete", "tetter", "tier", "tipiti", "tirr", "titer", "titre", "tittie", "treitre", "treppe", "tret", "tript"]},
{"pangram": ["menow", "women"], "validLetters": ["e", "m", "n", "o", "w"], "answers": ["emmew", "enew", "ennew", "enow", "memo", "mene", "mennon", "mmmm", "mnem", "mome", "momme", "mone", "moneme", "neem", "nene", "neon", "nomen", "weemen", "ween", "weewee", "weewow", "wone", "woom", "woon"]},
{"pangram": ["jiggling", "jingling"], "validLetters": ["g", "i", "j", "l", "n"], "answers": ["ging", "jigging", "jinjili", "lignin", "linin", "lining", "niggling", "nill", "ning"]},
{"pangram": ["kookery", "reyoke", "rookery"], "validLetters": ["e", "k", "o", "r", "y"], "answers": ["eyey", "eyrer", "eyry", "erke", "error", "yere", "yerk", "yoke", "keyer", "kero", "kook", "korero", "orrery", "reek", "reeker", "reeky", "ryke", "roke", "rokee", "roky", "rook"]},
{"pangram": ["leerily"], "validLetters": ["e", "i", "l", "r", "y"], "answers": ["eelery", "eely", "eerie", "eyey", "eyrer", "eyry", "eyrir", "yeel", "yere", "yirr", "leer", "leerier", "lier", "lyre", "rely", "relier", "rereel", "rile", "rille", "rilly"]},
{"pangram": ["fudge", "fugued"], "validLetters": ["d", "e", "f", "g", "u"], "answers": ["dedd", "deeded", "deedeed", "degged", "degu", "dude", "duffed", "dugdug", "edged", "egged", "euge", "feed", "feeded", "feudee", "feued", "fuge", "fugu", "gedd", "gegg", "gudge", "guff", "gugu"]},
{"pangram": ["grump"], "validLetters": ["g", "m", "p", "r", "u"], "answers": ["grum", "gugu", "gump", "gurr", "guru", "mmmm", "mumm", "murr", "muumuu", "purr", "ruru"]}
]
}